scrapy_autoextract/__init__.py
scrapy_autoextract/__version__.py
scrapy_autoextract/cache.py
scrapy_autoextract/errors.py
scrapy_autoextract/middlewares.py
scrapy_autoextract/providers.py
scrapy_autoextract/slot_semaphore.py
scrapy_autoextract/task_manager.py
scrapy_autoextract/utils.py
tests/__init__.py
tests/conftest.py
tests/test_autoextract.py
tests/test_errors.py
tests/test_providers.py
tests/test_slot_semaphore.py
tests/test_task_manager.py
tests/utils.py
scrapy_autoextract-0.7.0.dist-info/LICENSE
scrapy_autoextract-0.7.0.dist-info/METADATA
scrapy_autoextract-0.7.0.dist-info/WHEEL
scrapy_autoextract-0.7.0.dist-info/top_level.txt
scrapy_autoextract-0.7.0.dist-info/RECORD
