Metadata-Version: 2.1
Name: scrapy-autoextract
Version: 0.7.0
Summary: Zyte Automatic Extraction API integration for Scrapy
Home-page: https://github.com/scrapinghub/scrapy-autoextract
Author: Zyte Group Ltd
Author-email: info@zyte.com
Maintainer: Zyte Group Ltd
Maintainer-email: info@zyte.com
License: UNKNOWN
Keywords: scrapy autoextract middleware
Platform: UNKNOWN
Classifier: Development Status :: 4 - Beta
Classifier: Environment :: Console
Classifier: Intended Audience :: Developers
Classifier: Natural Language :: English
Classifier: Operating System :: OS Independent
Classifier: License :: OSI Approved :: BSD License
Classifier: Programming Language :: Python :: 3 :: Only
Classifier: Programming Language :: Python :: 3.6
Classifier: Programming Language :: Python :: 3.7
Classifier: Programming Language :: Python :: 3.8
Classifier: Programming Language :: Python :: 3.9
Classifier: Framework :: Scrapy
Requires-Dist: autoextract-poet (>=0.3.0)
Requires-Dist: zyte-autoextract (>=0.7.0)
Requires-Dist: scrapy-poet (>=0.2.0)
Requires-Dist: aiohttp
Requires-Dist: tldextract
Requires-Dist: sqlitedict (>=1.7.0)
